ONNX2RDF/__init__.py
ONNX2RDF/clean_model.py
ONNX2RDF/json_util.py
ONNX2RDF/parser.py
ONNX2RDF/warnings_thread_safe.py
ONNX2RDF/mappings/mapper_yarr.yaml
ONNX2RDF/ontology/onnx_ontology.drawio.png
ONNX2RDF/ontology/onnx_ontology.drawio.svg
ONNX2RDF/ontology/onnx_ontology.drawio.xml
ONNX2RDF/ontology/onnx_ontology.jpg
ONNX2RDF/ontology/onnx_ontology.webp
ONNX2RDF/ontology/ontology.ttl
ONNX2RDF/pre_process_module/__init__.py
ONNX2RDF/pre_process_module/pre_process.py
ONNX2RDF/pre_process_module/repair_functions/__init__.py
ONNX2RDF/pre_process_module/repair_functions/check_functions.py
ONNX2RDF/pre_process_module/repair_functions/repair_opsets.py
ONNX2RDF/pre_process_module/repair_nodes/__init__.py
ONNX2RDF/pre_process_module/repair_nodes/node_connections.py
ONNX2RDF/pre_process_module/repair_nodes/repair_nodes_base.py
ONNX2RDF/pre_process_module/repair_types/__init__.py
ONNX2RDF/pre_process_module/repair_types/reapair_value_info.py
ONNX2RDF/pre_process_module/repair_types/repair_annotation.py
ONNX2RDF/pre_process_module/repair_types/repair_attributes.py
ONNX2RDF/pre_process_module/repair_types/repair_dims.py
ONNX2RDF/pre_process_module/repair_types/repair_initializer.py
ONNX2RDF/pre_process_module/repair_types/repair_metadata_prop.py
ONNX2RDF/pre_process_module/repair_types/repair_tensor.py
ONNX2RDF/pre_process_module/repair_types/repair_type_proto.py
ONNX2RDF/pre_process_module/util_process/__init__.py
ONNX2RDF/pre_process_module/util_process/data.py
ONNX2RDF/pre_process_module/util_process/operators.py
ONNX2RDF/pre_process_module/util_process/util.py
onnx_2_rdf-0.1.4.dist-info/licenses/LICENSE
onnx_2_rdf-0.1.4.dist-info/METADATA
onnx_2_rdf-0.1.4.dist-info/WHEEL
onnx_2_rdf-0.1.4.dist-info/entry_points.txt
onnx_2_rdf-0.1.4.dist-info/top_level.txt
onnx_2_rdf-0.1.4.dist-info/RECORD
