Metadata-Version: 2.4
Name: onnx_2_rdf
Version: 0.1.4
Summary: ONNX to rdf parser
Author-email: Jorge M <jorge.martin.izquierdo@upm.es>
License: Apache-2.0
Project-URL: homepage, https://github.com/JorgeMIng/ONNX2RDF
Project-URL: download, https://github.com/JorgeMIng/ONNX2RDF/archive/refs/tags/v0.1.3.zip
Project-URL: issues, https://github.com/JorgeMIng/ONNX2RDF/issues
Keywords: ONNX,RDF,Semantic Web,Machine Learning,Ontology,Linked Data
Classifier: Development Status :: 4 - Beta
Classifier: Intended Audience :: Developers
Classifier: Intended Audience :: Science/Research
Classifier: Topic :: Scientific/Engineering :: Artificial Intelligence
Classifier: Topic :: Scientific/Engineering :: Information Analysis
Classifier: Topic :: Software Development :: Build Tools
Classifier: Topic :: Software Development :: Libraries :: Python Modules
Classifier: License :: OSI Approved :: Apache Software License
Classifier: Programming Language :: Python :: 3.13
Classifier: Natural Language :: English
Classifier: Operating System :: Microsoft :: Windows
Classifier: Operating System :: POSIX :: Linux
Requires-Python: >=3.13
License-File: LICENSE
Requires-Dist: onnx==1.18.0
Requires-Dist: onnxruntime==1.22.0
Requires-Dist: ruamel.yaml==0.18.10
Requires-Dist: pathvalidate==3.2.3
Dynamic: license-file
